[{"unixtime": 1685318540, "rank": 3292, "localRank": 15, "league": "wood2"}, {"unixtime": 1685319140, "rank": 3293, "localRank": 16, "league": "wood2"}, {"unixtime": 1685319740, "rank": 3290, "localRank": 10, "league": "wood2"}, {"unixtime": 1685320340, "rank": 3291, "localRank": 11, "league": "wood2"}, {"unixtime": 1685320940, "rank": 3292, "localRank": 10, "league": "wood2"}, {"unixtime": 1685321541, "rank": 3295, "localRank": 10, "league": "wood2"}, {"unixtime": 1685322141, "rank": 3296, "localRank": 10, "league": "wood2"}, {"unixtime": 1685322741, "rank": 3297, "localRank": 10, "league": "wood2"}, {"unixtime": 1685323341, "rank": 3298, "localRank": 10, "league": "wood2"}, {"unixtime": 1685323941, "rank": 3304, "localRank": 14, "league": "wood2"}, {"unixtime": 1685324541, "rank": 3306, "localRank": 12, "league": "wood2"}, {"unixtime": 1685325141, "rank": 3305, "localRank": 10, "league": "wood2"}, {"unixtime": 1685325741, "rank": 3306, "localRank": 9, "league": "wood2"}, {"unixtime": 1685326341, "rank": 3306, "localRank": 8, "league": "wood2"}, {"unixtime": 1685326941, "rank": 3307, "localRank": 8, "league": "wood2"}, {"unixtime": 1685327541, "rank": 3307, "localRank": 8, "league": "wood2"}, {"unixtime": 1685328141, "rank": 3307, "localRank": 8, "league": "wood2"}, {"unixtime": 1685328741, "rank": 3311, "localRank": 10, "league": "wood2"}, {"unixtime": 1685329341, "rank": 3312, "localRank": 10, "league": "wood2"}, {"unixtime": 1685329941, "rank": 3312, "localRank": 9, "league": "wood2"}, {"unixtime": 1685330541, "rank": 3311, "localRank": 8, "league": "wood2"}, {"unixtime": 1685331142, "rank": 3313, "localRank": 8, "league": "wood2"}, {"unixtime": 1685331742, "rank": 3314, "localRank": 8, "league": "wood2"}, {"unixtime": 1685332342, "rank": 3314, "localRank": 8, "league": "wood2"}, {"unixtime": 1685332942, "rank": 3315, "localRank": 8, "league": "wood2"}, {"unixtime": 1685333542, "rank": 3316, "localRank": 9, "league": "wood2"}, {"unixtime": 1685334142, "rank": 3317, "localRank": 7, "league": "wood2"}, {"unixtime": 1685334742, "rank": 3317, "localRank": 7, "league": "wood2"}, {"unixtime": 1685335342, "rank": 3317, "localRank": 7, "league": "wood2"}, {"unixtime": 1685335942, "rank": 3318, "localRank": 7, "league": "wood2"}, {"unixtime": 1685336542, "rank": 3319, "localRank": 7, "league": "wood2"}, {"unixtime": 1685337142, "rank": 3322, "localRank": 8, "league": "wood2"}, {"unixtime": 1685337742, "rank": 3322, "localRank": 8, "league": "wood2"}, {"unixtime": 1685338342, "rank": 3322, "localRank": 8, "league": "wood2"}, {"unixtime": 1685338942, "rank": 3323, "localRank": 8, "league": "wood2"}, {"unixtime": 1685339542, "rank": 3326, "localRank": 11, "league": "wood2"}, {"unixtime": 1685340142, "rank": 3323, "localRank": 8, "league": "wood2"}, {"unixtime": 1685340742, "rank": 3322, "localRank": 7, "league": "wood2"}, {"unixtime": 1685341342, "rank": 3322, "localRank": 7, "league": "wood2"}, {"unixtime": 1685341943, "rank": 3322, "localRank": 7, "league": "wood2"}, {"unixtime": 1685342543, "rank": 3323, "localRank": 6, "league": "wood2"}, {"unixtime": 1685343143, "rank": 3324, "localRank": 7, "league": "wood2"}, {"unixtime": 1685343743, "rank": 3328, "localRank": 9, "league": "wood2"}, {"unixtime": 1685344343, "rank": 3330, "localRank": 8, "league": "wood2"}, {"unixtime": 1685344943, "rank": 3332, "localRank": 10, "league": "wood2"}, {"unixtime": 1685345543, "rank": 3331, "localRank": 6, "league": "wood2"}, {"unixtime": 1685346143, "rank": 3332, "localRank": 5, "league": "wood2"}, {"unixtime": 1685346743, "rank": 3337, "localRank": 8, "league": "wood2"}, {"unixtime": 1685347343, "rank": 3337, "localRank": 8, "league": "wood2"}, {"unixtime": 1685347944, "rank": 3341, "localRank": 9, "league": "wood2"}, {"unixtime": 1685348544, "rank": 3343, "localRank": 7, "league": "wood2"}, {"unixtime": 1685349144, "rank": 3345, "localRank": 8, "league": "wood2"}, {"unixtime": 1685349744, "rank": 3347, "localRank": 8, "league": "wood2"}, {"unixtime": 1685350344, "rank": 3351, "localRank": 10, "league": "wood2"}, {"unixtime": 1685350944, "rank": 3350, "localRank": 8, "league": "wood2"}, {"unixtime": 1685351544, "rank": 3353, "localRank": 2, "league": "wood2"}, {"unixtime": 1685352144, "rank": 3355, "localRank": 3, "league": "wood2"}, {"unixtime": 1685920059, "rank": 4624, "localRank": 1000, "league": "wood1"}, {"unixtime": 1685920659, "rank": 4625, "localRank": 997, "league": "wood1"}, {"unixtime": 1685930260, "rank": 4642, "localRank": 999, "league": "wood1"}, {"unixtime": 1685934460, "rank": 4646, "localRank": 1000, "league": "wood1"}, {"unixtime": 1685935060, "rank": 4645, "localRank": 999, "league": "wood1"}, {"unixtime": 1685935660, "rank": 4645, "localRank": 998, "league": "wood1"}, {"unixtime": 1685936860, "rank": 4645, "localRank": 998, "league": "wood1"}, {"unixtime": 1685937461, "rank": 4644, "localRank": 997, "league": "wood1"}, {"unixtime": 1685938061, "rank": 4644, "localRank": 995, "league": "wood1"}, {"unixtime": 1685938661, "rank": 4645, "localRank": 996, "league": "wood1"}, {"unixtime": 1685939261, "rank": 4645, "localRank": 996, "league": "wood1"}, {"unixtime": 1685939861, "rank": 4646, "localRank": 997, "league": "wood1"}, {"unixtime": 1685940461, "rank": 4645, "localRank": 996, "league": "wood1"}, {"unixtime": 1685941061, "rank": 4646, "localRank": 995, "league": "wood1"}, {"unixtime": 1685941661, "rank": 4646, "localRank": 995, "league": "wood1"}, {"unixtime": 1685942261, "rank": 4648, "localRank": 997, "league": "wood1"}, {"unixtime": 1685942861, "rank": 4647, "localRank": 996, "league": "wood1"}, {"unixtime": 1685943461, "rank": 4647, "localRank": 996, "league": "wood1"}, {"unixtime": 1685944061, "rank": 4649, "localRank": 997, "league": "wood1"}, {"unixtime": 1685944661, "rank": 4650, "localRank": 997, "league": "wood1"}, {"unixtime": 1685945261, "rank": 4650, "localRank": 997, "league": "wood1"}, {"unixtime": 1685945862, "rank": 4651, "localRank": 997, "league": "wood1"}, {"unixtime": 1685946462, "rank": 4651, "localRank": 997, "league": "wood1"}, {"unixtime": 1685947062, "rank": 4651, "localRank": 997, "league": "wood1"}, {"unixtime": 1685947662, "rank": 4651, "localRank": 997, "league": "wood1"}, {"unixtime": 1685948262, "rank": 4651, "localRank": 996, "league": "wood1"}, {"unixtime": 1685948862, "rank": 4650, "localRank": 995, "league": "wood1"}, {"unixtime": 1685949462, "rank": 4651, "localRank": 996, "league": "wood1"}, {"unixtime": 1685950062, "rank": 4654, "localRank": 999, "league": "wood1"}, {"unixtime": 1685950662, "rank": 4656, "localRank": 1000, "league": "wood1"}, {"unixtime": 1685951262, "rank": 4656, "localRank": 999, "league": "wood1"}, {"unixtime": 1685951932, "rank": 4657, "localRank": 997, "league": "wood1"}]