[{"unixtime": 1718322051, "rank": 1779, "localRank": 273, "league": "wood1"}, {"unixtime": 1718322651, "rank": 1781, "localRank": 273, "league": "wood1"}, {"unixtime": 1718323251, "rank": 1781, "localRank": 273, "league": "wood1"}, {"unixtime": 1718323851, "rank": 1782, "localRank": 272, "league": "wood1"}, {"unixtime": 1718324451, "rank": 1782, "localRank": 270, "league": "wood1"}, {"unixtime": 1718325051, "rank": 1782, "localRank": 270, "league": "wood1"}, {"unixtime": 1718325651, "rank": 1784, "localRank": 271, "league": "wood1"}, {"unixtime": 1718326251, "rank": 1785, "localRank": 271, "league": "wood1"}, {"unixtime": 1718326851, "rank": 1785, "localRank": 270, "league": "wood1"}, {"unixtime": 1718327451, "rank": 1787, "localRank": 270, "league": "wood1"}, {"unixtime": 1718328051, "rank": 1789, "localRank": 271, "league": "wood1"}, {"unixtime": 1718328651, "rank": 1791, "localRank": 271, "league": "wood1"}, {"unixtime": 1718329251, "rank": 1791, "localRank": 271, "league": "wood1"}, {"unixtime": 1718329851, "rank": 1793, "localRank": 273, "league": "wood1"}, {"unixtime": 1718330451, "rank": 1793, "localRank": 272, "league": "wood1"}, {"unixtime": 1718331051, "rank": 1793, "localRank": 272, "league": "wood1"}, {"unixtime": 1718331651, "rank": 1793, "localRank": 271, "league": "wood1"}, {"unixtime": 1718332251, "rank": 1793, "localRank": 271, "league": "wood1"}, {"unixtime": 1718332851, "rank": 1793, "localRank": 270, "league": "wood1"}, {"unixtime": 1718333451, "rank": 1793, "localRank": 269, "league": "wood1"}, {"unixtime": 1718334051, "rank": 1794, "localRank": 269, "league": "wood1"}, {"unixtime": 1718334651, "rank": 1794, "localRank": 269, "league": "wood1"}, {"unixtime": 1718335251, "rank": 1794, "localRank": 269, "league": "wood1"}, {"unixtime": 1718335851, "rank": 1795, "localRank": 268, "league": "wood1"}, {"unixtime": 1718336451, "rank": 1797, "localRank": 269, "league": "wood1"}, {"unixtime": 1718337051, "rank": 1798, "localRank": 269, "league": "wood1"}, {"unixtime": 1718337651, "rank": 1798, "localRank": 269, "league": "wood1"}, {"unixtime": 1718338251, "rank": 1799, "localRank": 269, "league": "wood1"}, {"unixtime": 1718338851, "rank": 1800, "localRank": 270, "league": "wood1"}, {"unixtime": 1718339451, "rank": 1800, "localRank": 269, "league": "wood1"}, {"unixtime": 1718340051, "rank": 1800, "localRank": 269, "league": "wood1"}, {"unixtime": 1718340651, "rank": 1800, "localRank": 269, "league": "wood1"}, {"unixtime": 1718341251, "rank": 1801, "localRank": 269, "league": "wood1"}, {"unixtime": 1718341851, "rank": 1803, "localRank": 270, "league": "wood1"}, {"unixtime": 1718342451, "rank": 1804, "localRank": 271, "league": "wood1"}, {"unixtime": 1718343051, "rank": 1804, "localRank": 271, "league": "wood1"}, {"unixtime": 1718343651, "rank": 1805, "localRank": 272, "league": "wood1"}, {"unixtime": 1718344251, "rank": 1804, "localRank": 271, "league": "wood1"}, {"unixtime": 1718344851, "rank": 1809, "localRank": 272, "league": "wood1"}, {"unixtime": 1718345451, "rank": 1811, "localRank": 271, "league": "wood1"}, {"unixtime": 1718346051, "rank": 1813, "localRank": 272, "league": "wood1"}, {"unixtime": 1718346651, "rank": 1815, "localRank": 274, "league": "wood1"}, {"unixtime": 1718347251, "rank": 1816, "localRank": 274, "league": "wood1"}, {"unixtime": 1718347851, "rank": 1817, "localRank": 275, "league": "wood1"}, {"unixtime": 1718348451, "rank": 1822, "localRank": 277, "league": "wood1"}, {"unixtime": 1718349051, "rank": 1826, "localRank": 276, "league": "wood1"}, {"unixtime": 1718349651, "rank": 1828, "localRank": 276, "league": "wood1"}, {"unixtime": 1718350251, "rank": 1831, "localRank": 277, "league": "wood1"}, {"unixtime": 1718350851, "rank": 1831, "localRank": 276, "league": "wood1"}, {"unixtime": 1718351451, "rank": 1833, "localRank": 274, "league": "wood1"}, {"unixtime": 1718352051, "rank": 1835, "localRank": 276, "league": "wood1"}, {"unixtime": 1718352651, "rank": 1836, "localRank": 277, "league": "wood1"}, {"unixtime": 1718353251, "rank": 1837, "localRank": 276, "league": "wood1"}, {"unixtime": 1718353851, "rank": 1838, "localRank": 277, "league": "wood1"}, {"unixtime": 1718354451, "rank": 1845, "localRank": 281, "league": "wood1"}, {"unixtime": 1718355051, "rank": 1847, "localRank": 279, "league": "wood1"}, {"unixtime": 1718355651, "rank": 1851, "localRank": 282, "league": "wood1"}, {"unixtime": 1718356251, "rank": 1851, "localRank": 281, "league": "wood1"}, {"unixtime": 1718356851, "rank": 1852, "localRank": 282, "league": "wood1"}, {"unixtime": 1718357451, "rank": 1856, "localRank": 284, "league": "wood1"}, {"unixtime": 1718358051, "rank": 1857, "localRank": 282, "league": "wood1"}, {"unixtime": 1718358651, "rank": 1860, "localRank": 283, "league": "wood1"}, {"unixtime": 1718359251, "rank": 1863, "localRank": 284, "league": "wood1"}, {"unixtime": 1718359851, "rank": 1869, "localRank": 284, "league": "wood1"}, {"unixtime": 1718360451, "rank": 1869, "localRank": 283, "league": "wood1"}, {"unixtime": 1718361051, "rank": 1875, "localRank": 286, "league": "wood1"}, {"unixtime": 1718361651, "rank": 1878, "localRank": 284, "league": "wood1"}, {"unixtime": 1718362251, "rank": 1879, "localRank": 285, "league": "wood1"}, {"unixtime": 1718362851, "rank": 1881, "localRank": 286, "league": "wood1"}, {"unixtime": 1718363451, "rank": 1884, "localRank": 286, "league": "wood1"}, {"unixtime": 1718364051, "rank": 1887, "localRank": 287, "league": "wood1"}, {"unixtime": 1718364651, "rank": 1886, "localRank": 285, "league": "wood1"}, {"unixtime": 1718365251, "rank": 1890, "localRank": 286, "league": "wood1"}, {"unixtime": 1718365851, "rank": 1894, "localRank": 288, "league": "wood1"}, {"unixtime": 1718366451, "rank": 1897, "localRank": 289, "league": "wood1"}, {"unixtime": 1718367051, "rank": 1899, "localRank": 290, "league": "wood1"}, {"unixtime": 1718367651, "rank": 1902, "localRank": 291, "league": "wood1"}, {"unixtime": 1718368251, "rank": 1906, "localRank": 287, "league": "wood1"}, {"unixtime": 1718368851, "rank": 1909, "localRank": 288, "league": "wood1"}, {"unixtime": 1718369451, "rank": 1911, "localRank": 285, "league": "wood1"}, {"unixtime": 1718370051, "rank": 1915, "localRank": 287, "league": "wood1"}, {"unixtime": 1718370651, "rank": 1918, "localRank": 285, "league": "wood1"}, {"unixtime": 1718371251, "rank": 1916, "localRank": 283, "league": "wood1"}, {"unixtime": 1718371851, "rank": 1920, "localRank": 285, "league": "wood1"}, {"unixtime": 1718372451, "rank": 1925, "localRank": 285, "league": "wood1"}, {"unixtime": 1718373051, "rank": 1924, "localRank": 284, "league": "wood1"}, {"unixtime": 1718373651, "rank": 1928, "localRank": 284, "league": "wood1"}, {"unixtime": 1718374251, "rank": 1916, "localRank": 290, "league": "wood1"}, {"unixtime": 1718374851, "rank": 1939, "localRank": 290, "league": "wood1"}, {"unixtime": 1718375451, "rank": 1941, "localRank": 292, "league": "wood1"}, {"unixtime": 1718376051, "rank": 1940, "localRank": 288, "league": "wood1"}, {"unixtime": 1718376651, "rank": 1945, "localRank": 290, "league": "wood1"}, {"unixtime": 1718377251, "rank": 1949, "localRank": 293, "league": "wood1"}, {"unixtime": 1718377851, "rank": 1949, "localRank": 293, "league": "wood1"}, {"unixtime": 1718378451, "rank": 1952, "localRank": 293, "league": "wood1"}, {"unixtime": 1718379051, "rank": 1952, "localRank": 293, "league": "wood1"}, {"unixtime": 1718379651, "rank": 1964, "localRank": 296, "league": "wood1"}, {"unixtime": 1718380251, "rank": 1968, "localRank": 296, "league": "wood1"}, {"unixtime": 1718381090, "rank": 1969, "localRank": 292, "league": "wood1"}, {"unixtime": 1718381690, "rank": 1972, "localRank": 293, "league": "wood1"}, {"unixtime": 1718382290, "rank": 1972, "localRank": 291, "league": "wood1"}, {"unixtime": 1718382890, "rank": 1973, "localRank": 291, "league": "wood1"}, {"unixtime": 1718383490, "rank": 1976, "localRank": 293, "league": "wood1"}, {"unixtime": 1718384090, "rank": 1980, "localRank": 292, "league": "wood1"}, {"unixtime": 1718384690, "rank": 1984, "localRank": 293, "league": "wood1"}, {"unixtime": 1718385290, "rank": 1987, "localRank": 296, "league": "wood1"}, {"unixtime": 1718385890, "rank": 1988, "localRank": 297, "league": "wood1"}, {"unixtime": 1718386490, "rank": 1993, "localRank": 300, "league": "wood1"}, {"unixtime": 1718387090, "rank": 1992, "localRank": 299, "league": "wood1"}, {"unixtime": 1718387690, "rank": 1992, "localRank": 299, "league": "wood1"}, {"unixtime": 1718388290, "rank": 1993, "localRank": 300, "league": "wood1"}, {"unixtime": 1718388890, "rank": 1997, "localRank": 302, "league": "wood1"}, {"unixtime": 1718389490, "rank": 2000, "localRank": 304, "league": "wood1"}, {"unixtime": 1718390090, "rank": 2004, "localRank": 304, "league": "wood1"}, {"unixtime": 1718390690, "rank": 2006, "localRank": 305, "league": "wood1"}, {"unixtime": 1718391290, "rank": 2006, "localRank": 303, "league": "wood1"}, {"unixtime": 1718391890, "rank": 1017, "localRank": 62, "league": "bronze"}, {"unixtime": 1718392490, "rank": 977, "localRank": 21, "league": "bronze"}, {"unixtime": 1718393090, "rank": 980, "localRank": 22, "league": "bronze"}, {"unixtime": 1718393690, "rank": 971, "localRank": 12, "league": "bronze"}, {"unixtime": 1718394290, "rank": 980, "localRank": 17, "league": "bronze"}, {"unixtime": 1718394890, "rank": 977, "localRank": 13, "league": "bronze"}, {"unixtime": 1718395490, "rank": 998, "localRank": 32, "league": "bronze"}, {"unixtime": 1718396090, "rank": 1007, "localRank": 40, "league": "bronze"}, {"unixtime": 1718396690, "rank": 1006, "localRank": 38, "league": "bronze"}, {"unixtime": 1718397290, "rank": 1003, "localRank": 32, "league": "bronze"}, {"unixtime": 1718397890, "rank": 1012, "localRank": 37, "league": "bronze"}, {"unixtime": 1718398490, "rank": 1004, "localRank": 28, "league": "bronze"}, {"unixtime": 1718399090, "rank": 1018, "localRank": 42, "league": "bronze"}, {"unixtime": 1718399690, "rank": 1018, "localRank": 42, "league": "bronze"}, {"unixtime": 1718400290, "rank": 1026, "localRank": 46, "league": "bronze"}, {"unixtime": 1718400890, "rank": 1027, "localRank": 43, "league": "bronze"}, {"unixtime": 1718401490, "rank": 1025, "localRank": 40, "league": "bronze"}, {"unixtime": 1718402090, "rank": 1032, "localRank": 44, "league": "bronze"}, {"unixtime": 1718402690, "rank": 1032, "localRank": 40, "league": "bronze"}, {"unixtime": 1718403290, "rank": 1035, "localRank": 41, "league": "bronze"}, {"unixtime": 1718403890, "rank": 1051, "localRank": 54, "league": "bronze"}, {"unixtime": 1718404490, "rank": 1049, "localRank": 50, "league": "bronze"}, {"unixtime": 1718405090, "rank": 1047, "localRank": 42, "league": "bronze"}, {"unixtime": 1718405690, "rank": 1041, "localRank": 20, "league": "bronze"}, {"unixtime": 1718406290, "rank": 1048, "localRank": 21, "league": "bronze"}, {"unixtime": 1718407490, "rank": 955, "localRank": 955, "league": "silver"}, {"unixtime": 1718408090, "rank": 948, "localRank": 948, "league": "silver"}, {"unixtime": 1718408690, "rank": 971, "localRank": 971, "league": "silver"}, {"unixtime": 1718409290, "rank": 977, "localRank": 977, "league": "silver"}, {"unixtime": 1718409890, "rank": 971, "localRank": 971, "league": "silver"}, {"unixtime": 1718410490, "rank": 975, "localRank": 975, "league": "silver"}, {"unixtime": 1718411090, "rank": 986, "localRank": 986, "league": "silver"}, {"unixtime": 1718411690, "rank": 982, "localRank": 982, "league": "silver"}, {"unixtime": 1718412290, "rank": 984, "localRank": 984, "league": "silver"}, {"unixtime": 1718412890, "rank": 988, "localRank": 988, "league": "silver"}, {"unixtime": 1718413490, "rank": 985, "localRank": 985, "league": "silver"}, {"unixtime": 1718414090, "rank": 987, "localRank": 987, "league": "silver"}, {"unixtime": 1718414690, "rank": 985, "localRank": 985, "league": "silver"}, {"unixtime": 1718415290, "rank": 987, "localRank": 987, "league": "silver"}, {"unixtime": 1718415890, "rank": 996, "localRank": 996, "league": "silver"}, {"unixtime": 1718418290, "rank": 998, "localRank": 998, "league": "silver"}, {"unixtime": 1718418890, "rank": 1000, "localRank": 1000, "league": "silver"}, {"unixtime": 1718419490, "rank": 1000, "localRank": 1000, "league": "silver"}, {"unixtime": 1718420090, "rank": 1000, "localRank": 1000, "league": "silver"}, {"unixtime": 1718420690, "rank": 990, "localRank": 990, "league": "silver"}, {"unixtime": 1718421290, "rank": 990, "localRank": 990, "league": "silver"}, {"unixtime": 1718421890, "rank": 996, "localRank": 996, "league": "silver"}, {"unixtime": 1718422490, "rank": 1000, "localRank": 1000, "league": "silver"}, {"unixtime": 1718423090, "rank": 1000, "localRank": 1000, "league": "silver"}, {"unixtime": 1718424890, "rank": 988, "localRank": 988, "league": "silver"}, {"unixtime": 1718425490, "rank": 987, "localRank": 987, "league": "silver"}, {"unixtime": 1718426090, "rank": 990, "localRank": 990, "league": "silver"}, {"unixtime": 1718426690, "rank": 997, "localRank": 997, "league": "silver"}, {"unixtime": 1718427290, "rank": 1000, "localRank": 1000, "league": "silver"}, {"unixtime": 1718427890, "rank": 984, "localRank": 984, "league": "silver"}, {"unixtime": 1718428490, "rank": 986, "localRank": 986, "league": "silver"}, {"unixtime": 1718429090, "rank": 988, "localRank": 988, "league": "silver"}, {"unixtime": 1718429690, "rank": 998, "localRank": 998, "league": "silver"}, {"unixtime": 1718432690, "rank": 1000, "localRank": 1000, "league": "silver"}, {"unixtime": 1718433890, "rank": 975, "localRank": 975, "league": "silver"}, {"unixtime": 1718434490, "rank": 978, "localRank": 978, "league": "silver"}, {"unixtime": 1718435090, "rank": 980, "localRank": 980, "league": "silver"}, {"unixtime": 1718435690, "rank": 996, "localRank": 996, "league": "silver"}, {"unixtime": 1718436290, "rank": 996, "localRank": 996, "league": "silver"}, {"unixtime": 1718436890, "rank": 997, "localRank": 997, "league": "silver"}, {"unixtime": 1718437490, "rank": 1000, "localRank": 1000, "league": "silver"}, {"unixtime": 1718438090, "rank": 996, "localRank": 996, "league": "silver"}, {"unixtime": 1718438690, "rank": 995, "localRank": 995, "league": "silver"}, {"unixtime": 1718441690, "rank": 989, "localRank": 989, "league": "silver"}, {"unixtime": 1718442290, "rank": 987, "localRank": 987, "league": "silver"}, {"unixtime": 1718442890, "rank": 993, "localRank": 993, "league": "silver"}, {"unixtime": 1718443490, "rank": 989, "localRank": 989, "league": "silver"}, {"unixtime": 1718444690, "rank": 1000, "localRank": 1000, "league": "silver"}, {"unixtime": 1718445290, "rank": 990, "localRank": 990, "league": "silver"}, {"unixtime": 1718445890, "rank": 990, "localRank": 990, "league": "silver"}, {"unixtime": 1718446490, "rank": 980, "localRank": 980, "league": "silver"}, {"unixtime": 1718447090, "rank": 985, "localRank": 985, "league": "silver"}, {"unixtime": 1719043490, "rank": 1750, "localRank": 997, "league": "silver"}, {"unixtime": 1719044090, "rank": 1744, "localRank": 991, "league": "silver"}, {"unixtime": 1719044690, "rank": 1738, "localRank": 985, "league": "silver"}, {"unixtime": 1719045290, "rank": 1738, "localRank": 985, "league": "silver"}, {"unixtime": 1719045890, "rank": 1738, "localRank": 985, "league": "silver"}, {"unixtime": 1719046490, "rank": 1737, "localRank": 984, "league": "silver"}, {"unixtime": 1719047090, "rank": 1738, "localRank": 985, "league": "silver"}, {"unixtime": 1719047690, "rank": 1739, "localRank": 986, "league": "silver"}, {"unixtime": 1719048290, "rank": 1740, "localRank": 987, "league": "silver"}, {"unixtime": 1719048890, "rank": 1740, "localRank": 987, "league": "silver"}, {"unixtime": 1719049490, "rank": 1741, "localRank": 988, "league": "silver"}, {"unixtime": 1719050090, "rank": 1740, "localRank": 987, "league": "silver"}, {"unixtime": 1719050690, "rank": 1740, "localRank": 987, "league": "silver"}, {"unixtime": 1719051290, "rank": 1746, "localRank": 993, "league": "silver"}, {"unixtime": 1719051890, "rank": 1741, "localRank": 987, "league": "silver"}, {"unixtime": 1719259720, "rank": 1995, "localRank": 998, "league": "silver"}, {"unixtime": 1719268720, "rank": 1986, "localRank": 973, "league": "silver"}, {"unixtime": 1719269320, "rank": 2000, "localRank": 986, "league": "silver"}, {"unixtime": 1719269920, "rank": 2010, "localRank": 994, "league": "silver"}, {"unixtime": 1719290320, "rank": 2032, "localRank": 1000, "league": "silver"}, {"unixtime": 1719290920, "rank": 2030, "localRank": 998, "league": "silver"}, {"unixtime": 1719291520, "rank": 2030, "localRank": 998, "league": "silver"}, {"unixtime": 1719292120, "rank": 2030, "localRank": 997, "league": "silver"}, {"unixtime": 1719292720, "rank": 2028, "localRank": 995, "league": "silver"}, {"unixtime": 1719300520, "rank": 2037, "localRank": 1000, "league": "silver"}, {"unixtime": 1719301720, "rank": 2040, "localRank": 1000, "league": "silver"}, {"unixtime": 1719302320, "rank": 2038, "localRank": 998, "league": "silver"}, {"unixtime": 1719302920, "rank": 2034, "localRank": 993, "league": "silver"}]