[{"unixtime": 1650636279, "rank": 2908, "localRank": 49, "league": "wood2"}, {"unixtime": 1650636915, "rank": 2901, "localRank": 23, "league": "wood2"}, {"unixtime": 1650637547, "rank": 2907, "localRank": 12, "league": "wood2"}, {"unixtime": 1650638178, "rank": 2925, "localRank": 10, "league": "wood2"}, {"unixtime": 1650638811, "rank": 2345, "localRank": 124, "league": "wood1"}, {"unixtime": 1650639445, "rank": 2305, "localRank": 63, "league": "wood1"}, {"unixtime": 1650640077, "rank": 2334, "localRank": 62, "league": "wood1"}, {"unixtime": 1650640709, "rank": 2330, "localRank": 48, "league": "wood1"}, {"unixtime": 1650641341, "rank": 2348, "localRank": 46, "league": "wood1"}, {"unixtime": 1650655891, "rank": 990, "localRank": 990, "league": "bronze"}, {"unixtime": 1650656522, "rank": 950, "localRank": 950, "league": "bronze"}, {"unixtime": 1650657153, "rank": 949, "localRank": 949, "league": "bronze"}, {"unixtime": 1650657784, "rank": 957, "localRank": 957, "league": "bronze"}, {"unixtime": 1650658415, "rank": 932, "localRank": 932, "league": "bronze"}, {"unixtime": 1650659046, "rank": 932, "localRank": 932, "league": "bronze"}, {"unixtime": 1650659677, "rank": 954, "localRank": 954, "league": "bronze"}, {"unixtime": 1650660309, "rank": 957, "localRank": 957, "league": "bronze"}, {"unixtime": 1650660940, "rank": 971, "localRank": 971, "league": "bronze"}, {"unixtime": 1650661570, "rank": 968, "localRank": 968, "league": "bronze"}, {"unixtime": 1650662205, "rank": 974, "localRank": 974, "league": "bronze"}, {"unixtime": 1650662837, "rank": 967, "localRank": 967, "league": "bronze"}, {"unixtime": 1650663474, "rank": 950, "localRank": 950, "league": "bronze"}, {"unixtime": 1650664109, "rank": 963, "localRank": 963, "league": "bronze"}, {"unixtime": 1650664740, "rank": 958, "localRank": 958, "league": "bronze"}, {"unixtime": 1650665371, "rank": 976, "localRank": 976, "league": "bronze"}, {"unixtime": 1650666002, "rank": 980, "localRank": 980, "league": "bronze"}, {"unixtime": 1650666636, "rank": 992, "localRank": 992, "league": "bronze"}, {"unixtime": 1650813982, "rank": 2002, "localRank": 548, "league": "bronze"}, {"unixtime": 1650814614, "rank": 2065, "localRank": 395, "league": "bronze"}, {"unixtime": 1650815250, "rank": 2096, "localRank": 254, "league": "bronze"}]